littlelink/__init__.py
littlelink/assets.json
littlelink/cli.py
littlelink/generate.py
littlelink-0.1.1.dist-info/entry_points.txt
littlelink-0.1.1.dist-info/METADATA
littlelink-0.1.1.dist-info/WHEEL
littlelink-0.1.1.dist-info/RECORD
